{"type":"FeatureCollection","features":[{"type":"Feature","properties":{"city":"Salzburg"},"geometry":{"coordinates":[13.04415461879941,47.80346538351975],"type":"Point"}},{"type":"Feature","properties":{"city":"Graz"},"geometry":{"coordinates":[15.428999120838085,47.07068991924575],"type":"Point"}},{"type":"Feature","properties":{"city":"Innsbuck"},"geometry":{"coordinates":[11.39935798604958,47.268996371258794],"type":"Point"}}]}